zuper_ipce.pyi
zuper_ipce.cpython-310-aarch64-linux-gnu.so
zuper_ipce_z7-7.3.2202161758.dist-info/METADATA
zuper_ipce_z7-7.3.2202161758.dist-info/entry_points.txt
zuper_ipce_z7-7.3.2202161758.dist-info/WHEEL
zuper_ipce_z7-7.3.2202161758.dist-info/top_level.txt
zuper_ipce_z7-7.3.2202161758.dist-info/zip-safe
zuper_ipce_z7-7.3.2202161758.dist-info/RECORD
